trajectory_supervisor/__init__.py
trajectory_supervisor/supervisor.py
trajectory_supervisor/helper_funcs/__init__.py
trajectory_supervisor/helper_funcs/src/__init__.py
trajectory_supervisor/helper_funcs/src/bound_trajectory.py
trajectory_supervisor/helper_funcs/src/export_traj.py
trajectory_supervisor/helper_funcs/src/lane_based_coordinate_system.py
trajectory_supervisor/helper_funcs/src/path_matching.py
trajectory_supervisor/helper_funcs/src/reachable_set_feasible_bound.py
trajectory_supervisor/helper_funcs/src/reachable_set_simple.py
trajectory_supervisor/helper_funcs/src/reachable_set_turn_limit.py
trajectory_supervisor/helper_funcs/src/shapely_conversions.py
trajectory_supervisor/helper_funcs/src/sync_data.py
trajectory_supervisor/helper_funcs/src/zone_loader_generic.py
trajectory_supervisor/supervisor_modules/__init__.py
trajectory_supervisor/supervisor_modules/supmod_RSS/__init__.py
trajectory_supervisor/supervisor_modules/supmod_RSS/src/__init__.py
trajectory_supervisor/supervisor_modules/supmod_RSS/src/acceleration_profile.py
trajectory_supervisor/supervisor_modules/supmod_RSS/src/obj_path_storage.py
trajectory_supervisor/supervisor_modules/supmod_RSS/src/supmod_RSS.py
trajectory_supervisor/supervisor_modules/supmod_dummy/__init__.py
trajectory_supervisor/supervisor_modules/supmod_dummy/src/__init__.py
trajectory_supervisor/supervisor_modules/supmod_dummy/src/supmod_dummy.py
trajectory_supervisor/supervisor_modules/supmod_friction/__init__.py
trajectory_supervisor/supervisor_modules/supmod_friction/src/__init__.py
trajectory_supervisor/supervisor_modules/supmod_friction/src/check_friction.py
trajectory_supervisor/supervisor_modules/supmod_friction/src/supmod_friction.py
trajectory_supervisor/supervisor_modules/supmod_guaranteed_occupancy_area/__init__.py
trajectory_supervisor/supervisor_modules/supmod_guaranteed_occupancy_area/src/__init__.py
trajectory_supervisor/supervisor_modules/supmod_guaranteed_occupancy_area/src/guar_occ_calc.py
trajectory_supervisor-0.26.dist-info/METADATA
trajectory_supervisor-0.26.dist-info/WHEEL
trajectory_supervisor-0.26.dist-info/top_level.txt
trajectory_supervisor-0.26.dist-info/RECORD
