Metadata-Version: 2.1
Name: trajectory-supervisor
Version: 0.26
Summary: Trajectory Supervisor
Home-page: UNKNOWN
Author: Tim Stahl
Author-email: tim.stahl@tum.de
License: UNKNOWN
Platform: UNKNOWN
Classifier: Programming Language :: Python :: 3
Classifier: Programming Language :: Python :: 3.5
Classifier: Programming Language :: Python :: 3.6
Classifier: Programming Language :: Python :: 3.7
Classifier: License :: OSI Approved :: GNU Lesser General Public License v3 (LGPLv3)
Classifier: Operating System :: OS Independent
Requires-Dist: numpy (>=1.18.1)
Requires-Dist: matplotlib (>=3.3.1)
Requires-Dist: scipy (>=1.3.3)
Requires-Dist: trajectory-planning-helpers (>=0.75)
Requires-Dist: scenario-testing-tools (>=0.82)
Requires-Dist: shapely (>=1.7.0)
Requires-Dist: scikit-learn (>=0.22.1)
Requires-Dist: dill (>=0.3.3)
